{
  "guid": "f36ecc87686a8144fbb0f278cf2892d2",
  "filename": "Ribbon+3",
  "ID": 785,
  "Name": "Ribbon",
  "Price": 1000,
  "Type": 5,
  "Icon": "icon_ribbon",
  "Attack": 0,
  "Magic": 0,
  "Defense": 0,
  "CritChance": 0,
  "CritDamage": 0,
  "Health": 380,
  "Mana": 46,
  "ManaRegeneration": 0,
  "DamageBonus": 0,
  "NonCritDamage": 0,
  "HealBonus": 0,
  "DodgeChance": 0,
  "Unique": 0,
  "OnlyUnshifted": 0,
  "OnlyFamiliars": 0,
  "UpgradesTo": {
    "fileID": 1837169550514311,
    "guid": "5dc90a05e46d33f448fb40336b8327b3",
    "type": 2
  },
  "UpgradeMaterials": [
    {
      "Item": {
        "fileID": 1175341146284385,
        "guid": "c40f1bca0d04ad54fb6bf1dfb5be9c2b",
        "type": 2
      },
      "Quantity": 2
    },
    {
      "Item": {
        "fileID": 1735445830266374,
        "guid": "40219434937e68b438cab2c0b83c648e",
        "type": 2
      },
      "Quantity": 1
    }
  ]
}