{
  "guid": "0c33ee853d3f2dc4d89268b6c0911678",
  "filename": "Scroll",
  "ID": 311,
  "Name": "Scroll",
  "Price": 200,
  "Type": 5,
  "Icon": "icon_scroll",
  "Attack": 0,
  "Magic": 8,
  "Defense": 0,
  "CritChance": 0,
  "CritDamage": 0,
  "Health": 0,
  "Mana": 0,
  "ManaRegeneration": 15,
  "DamageBonus": 0,
  "NonCritDamage": 0,
  "HealBonus": 0,
  "DodgeChance": 0,
  "Unique": 0,
  "OnlyUnshifted": 0,
  "OnlyFamiliars": 0,
  "UpgradesTo": {
    "fileID": 1830147145699316,
    "guid": "5b639abf762ae95478cd31f27d972aca",
    "type": 2
  },
  "UpgradeMaterials": [
    {
      "Item": {
        "fileID": 1832258850283049,
        "guid": "cc2be5e14f6acfe4dba2e8d78a7a9bd0",
        "type": 2
      },
      "Quantity": 2
    },
    {
      "Item": {
        "fileID": 1938666508179504,
        "guid": "b8fd7e7e353ef0b41904cf951d27c922",
        "type": 2
      },
      "Quantity": 1
    }
  ]
}