{
  "guid": "6410abe0208e47748bd745da600584be",
  "filename": "Scythe+2",
  "ID": 1359,
  "Name": "Scythe",
  "Price": 3500,
  "Type": 0,
  "Icon": "icon_scythe",
  "Attack": 70,
  "Magic": 80,
  "Defense": 0,
  "CritChance": 0.05,
  "CritDamage": 0.19,
  "Health": 0,
  "Mana": 0,
  "ManaRegeneration": 0,
  "DamageBonus": 0,
  "NonCritDamage": 0,
  "HealBonus": 0,
  "DodgeChance": 0,
  "Unique": 1,
  "OnlyUnshifted": 0,
  "OnlyFamiliars": 0,
  "UpgradesTo": {
    "fileID": 1946754352371018,
    "guid": "4476d7860ac08fd4d8392a8bfe91bb4d",
    "type": 2
  },
  "UpgradeMaterials": [
    {
      "Item": {
        "fileID": 1287074701737878,
        "guid": "4cf122e3d9c9c3740a108f1e890998d7",
        "type": 2
      },
      "Quantity": 2
    },
    {
      "Item": {
        "fileID": 1430211027732074,
        "guid": "eef6eb4f3acbd5c49b57c6ba45ddf388",
        "type": 2
      },
      "Quantity": 1
    }
  ]
}