{
  "guid": "c7418105aed82c54394c9c5433ab0cf4",
  "filename": "SustainRing+5",
  "ID": 1372,
  "Name": "Sustain Ring",
  "Price": 2000,
  "Type": 4,
  "Icon": "icon_ring",
  "Attack": 0,
  "Magic": 0,
  "Defense": 0,
  "CritChance": 0,
  "CritDamage": 0,
  "Health": 0,
  "Mana": 0,
  "ManaRegeneration": 60,
  "DamageBonus": 0,
  "NonCritDamage": 0,
  "HealBonus": 0,
  "DodgeChance": 0,
  "Unique": 0,
  "OnlyUnshifted": 0,
  "OnlyFamiliars": 0,
  "UpgradesTo": {
    "fileID": 0
  },
  "UpgradeMaterials": []
}