{
  "guid": "e6a32a98a2709544c9e05d3dd7f7faa6",
  "filename": "VitalRing+2",
  "ID": 387,
  "Name": "Vital ring",
  "Price": 600,
  "Type": 4,
  "Icon": "icon_ring",
  "Attack": 0,
  "Magic": 0,
  "Defense": 0,
  "CritChance": 0,
  "CritDamage": 0,
  "Health": 380,
  "Mana": 0,
  "ManaRegeneration": 0,
  "DamageBonus": 0,
  "NonCritDamage": 0,
  "HealBonus": 0,
  "DodgeChance": 0,
  "Unique": 0,
  "OnlyUnshifted": 0,
  "OnlyFamiliars": 0,
  "UpgradesTo": {
    "fileID": 1804105078939905,
    "guid": "c74b575b68258f54d8a3f14f87b0da72",
    "type": 2
  },
  "UpgradeMaterials": [
    {
      "Item": {
        "fileID": 1236254572456791,
        "guid": "907eade581dbacc4ebbf3880173e9561",
        "type": 2
      },
      "Quantity": 1
    },
    {
      "Item": {
        "fileID": 1095882204890249,
        "guid": "4260bad0d04fad04083cee2fdf1c6b1c",
        "type": 2
      },
      "Quantity": 1
    }
  ]
}