{
  "guid": "11a63779e5a63a845a786c62e09045fb",
  "filename": "Catzerker",
  "ID": 238,
  "Name": "Catzerker",
  "baseStats": {
    "attack": 7,
    "magic": 4,
    "defense": 2,
    "health": 5,
    "mana": 4
  },
  "lightShift": {
    "attack": 1,
    "magic": 3,
    "defense": 1,
    "health": 2,
    "mana": 1
  },
  "darkShift": {
    "attack": 2,
    "magic": 2,
    "defense": 1,
    "health": 0,
    "mana": 3
  },
  "PortraitOffset": {
    "x": 5,
    "true": 3
  },
  "DifficultyRating": 2,
  "ArmyRating": 1,
  "RewardsCommon": [
    {
      "fileID": 1832258850283049,
      "guid": "cc2be5e14f6acfe4dba2e8d78a7a9bd0",
      "type": 2
    },
    {
      "fileID": 1104728274545518,
      "guid": "cfb61127c07759b47a5e9f24abe50ce7",
      "type": 2
    }
  ],
  "RewardsRare": [
    {
      "fileID": 1979148939231785,
      "guid": "fb7806c89741472478f451cd10abf730",
      "type": 2
    },
    {
      "fileID": 1866770686007546,
      "guid": "d3990c12ccd08a249b8446fcf5786a3c",
      "type": 2
    },
    {
      "fileID": 1728813171538540,
      "guid": "1348ac757402e2049ae9a68f398e4218",
      "type": 2
    }
  ],
  "StartLevel": 5,
  "FlyingOffset": 0,
  "MenuOffset": 0,
  "FlyingWaveMovement": 1,
  "JumpOffset": 0,
  "JumpFrequence": 0.3,
  "ShowParticlesInMenus": 1,
  "ExploreAction": {
    "fileID": 1646865771904386,
    "guid": "5e4718a36983e1d429bfb52dd7ed90b3",
    "type": 2
  },
  "ExploreActionMountAbility": {
    "fileID": 0
  },
  "ExploreActionExploreAbility": {
    "fileID": 0
  },
  "CenterOffset": {
    "x": 0,
    "true": 0
  },
  "PortraitAnimation": {
    "fileID": 0
  },
  "TargetArrowOffest": {
    "x": -12,
    "true": 0,
    "z": 0
  },
  "MonsterTypes": "070000000f000000",
  "NormalParticles": [],
  "LightParticles": [],
  "DarkParticles": [],
  "SpecialEvolutionId": 0,
  "MonsterSize": 0,
  "_IsEvolved": 0,
  "BaseSkills": [
    {
      "fileID": 1663222006699508,
      "guid": "55c68f2297e71354ea99aa9aa98837ff",
      "type": 2
    },
    {
      "fileID": 1246640935719246,
      "guid": "898f82535841d4c4cb00919f684e5888",
      "type": 2
    },
    {
      "fileID": 1936627760160920,
      "guid": "00e2ec08f8dcb17478c1bd3e6795fd53",
      "type": 2
    },
    {
      "fileID": 1379159313698690,
      "guid": "a23ac66630074714688a6bccca68c1b1",
      "type": 2
    }
  ],
  "AISkills": [
    {
      "fileID": 1738216089424885,
      "guid": "f91e4952be69b734494ff8968a9ade73",
      "type": 2
    }
  ],
  "AdvancedAILevelReq": 10,
  "AdvancedAISkills": [],
  "ChampionSkills": [],
  "Ultimates": [
    {
      "fileID": 1913071607404626,
      "guid": "297bd04f5ff6fc74fafde5fb2d7180e2",
      "type": 2
    },
    {
      "fileID": 1332087868471981,
      "guid": "e733c0e031bcd1a4a8f664cf6483874f",
      "type": 2
    },
    {
      "fileID": 1289704341483935,
      "guid": "47b6306dda881814a97e14500993a7bd",
      "type": 2
    }
  ],
  "LightSkill": {
    "fileID": 1179377711581307,
    "guid": "b9caabb8e3d061d40ac3150874c834b1",
    "type": 2
  },
  "DarkSkill": {
    "fileID": 1397011885445541,
    "guid": "01d1ad350d21c2d4bb95131d972b8ebd",
    "type": 2
  },
  "Tier1Skills": [
    {
      "fileID": 1663222006699508,
      "guid": "55c68f2297e71354ea99aa9aa98837ff",
      "type": 2
    }
  ],
  "Tier2Skills": [
    {
      "fileID": 1348210952285528,
      "guid": "88fb42c14c7cde44ab2c6bbcb916dd97",
      "type": 2
    },
    {
      "fileID": 1843815530327542,
      "guid": "ec292d04f8d72bd41a8fdf50c5f2bd43",
      "type": 2
    },
    {
      "fileID": 1046187329209521,
      "guid": "be50d663a2c42184a9127c2922bdebf1",
      "type": 2
    }
  ],
  "Tier3Skills": [
    {
      "fileID": 1093982331588194,
      "guid": "bc94dbb5e4c969d4182a804be1835c3b",
      "type": 2
    },
    {
      "fileID": 1859521087242773,
      "guid": "e30631c6bce31b8428182b668bd12473",
      "type": 2
    },
    {
      "fileID": 1955550795575206,
      "guid": "6cf7e2dc91e400444912d62d1683a836",
      "type": 2
    },
    {
      "fileID": 1642336900286206,
      "guid": "ce1c68724db3d4c4792c458bdcc69059",
      "type": 2
    }
  ],
  "Tier4Skills": [
    {
      "fileID": 1681028736617808,
      "guid": "c9c8e41d30c9d0a40a95190d8b129196",
      "type": 2
    },
    {
      "fileID": 1276224725963918,
      "guid": "8b2f840a6c5b0bd468e0dd2eaf942e81",
      "type": 2
    },
    {
      "fileID": 1794409188049869,
      "guid": "5067e38201634084dae5c3ab571dd6d0",
      "type": 2
    },
    {
      "fileID": 1107225715918854,
      "guid": "186abcea8da142b4086d311974b8ecfd",
      "type": 2
    }
  ],
  "Tier5Skills": [
    {
      "fileID": 1428836100645324,
      "guid": "399367ff9c0bfde44882c523cdc67cd8",
      "type": 2
    },
    {
      "fileID": 1878705178519613,
      "guid": "03734e18a8223be4482e0e23ca2f477a",
      "type": 2
    },
    {
      "fileID": 1296165490498852,
      "guid": "1639172c2d846294bbe0885a54593ae7",
      "type": 2
    },
    {
      "fileID": 1618223174622287,
      "guid": "ae8bb40b86104c5468fd4ec006174dd9",
      "type": 2
    }
  ],
  "Tier1Skills__1": [
    {
      "fileID": 1246640935719246,
      "guid": "898f82535841d4c4cb00919f684e5888",
      "type": 2
    }
  ],
  "Tier2Skills__1": [
    {
      "fileID": 1177920882222364,
      "guid": "2e9f8a647c4722f449565fde2e32ef9d",
      "type": 2
    },
    {
      "fileID": 1552734767132386,
      "guid": "54129cbd956f728439166f5039289607",
      "type": 2
    },
    {
      "fileID": 1832746634248003,
      "guid": "f746d869a51636f4a8909ed281cc8a10",
      "type": 2
    }
  ],
  "Tier3Skills__1": [
    {
      "fileID": 1263765811182381,
      "guid": "275997d5f64365143b3f7c66063ee5fa",
      "type": 2
    },
    {
      "fileID": 1531590619305270,
      "guid": "46b3b99c2fa04e74f8360968548b2d36",
      "type": 2
    },
    {
      "fileID": 1843815530327542,
      "guid": "ec292d04f8d72bd41a8fdf50c5f2bd43",
      "type": 2
    },
    {
      "fileID": 1552734767132386,
      "guid": "54129cbd956f728439166f5039289607",
      "type": 2
    }
  ],
  "Tier4Skills__1": [
    {
      "fileID": 1085898870576219,
      "guid": "bc6455fb2e1d6ef48abb141124ab08a6",
      "type": 2
    },
    {
      "fileID": 1479835260779578,
      "guid": "12a081403be777643a91348c0eeb3926",
      "type": 2
    },
    {
      "fileID": 1642336900286206,
      "guid": "ce1c68724db3d4c4792c458bdcc69059",
      "type": 2
    },
    {
      "fileID": 1977394999042118,
      "guid": "a5c21b48d39614f409fd8dd5c694d002",
      "type": 2
    }
  ],
  "Tier5Skills__1": [
    {
      "fileID": 1832505366857474,
      "guid": "3453d53376b1fbd4ba1dfff8a57584cb",
      "type": 2
    },
    {
      "fileID": 1366176079209518,
      "guid": "7411558f11dafb740bc0d00b135bea22",
      "type": 2
    },
    {
      "fileID": 1712345910789295,
      "guid": "1872ce802e75a2b4682f8345b0c3585f",
      "type": 2
    },
    {
      "fileID": 1977394999042118,
      "guid": "a5c21b48d39614f409fd8dd5c694d002",
      "type": 2
    }
  ],
  "Tier1Skills__2": [
    {
      "fileID": 1738216089424885,
      "guid": "f91e4952be69b734494ff8968a9ade73",
      "type": 2
    }
  ],
  "Tier2Skills__2": [
    {
      "fileID": 1624721887418744,
      "guid": "e5aa6fb23c0a0d34eba7a1bff010935b",
      "type": 2
    },
    {
      "fileID": 1046187329209521,
      "guid": "be50d663a2c42184a9127c2922bdebf1",
      "type": 2
    },
    {
      "fileID": 1296165490498852,
      "guid": "1639172c2d846294bbe0885a54593ae7",
      "type": 2
    }
  ],
  "Tier3Skills__2": [
    {
      "fileID": 1731515195765440,
      "guid": "9037c2a9d3eb3d74b99f0d7f21103057",
      "type": 2
    },
    {
      "fileID": 1642336900286206,
      "guid": "ce1c68724db3d4c4792c458bdcc69059",
      "type": 2
    },
    {
      "fileID": 1832746634248003,
      "guid": "f746d869a51636f4a8909ed281cc8a10",
      "type": 2
    }
  ],
  "Tier4Skills__2": [
    {
      "fileID": 1974223868971265,
      "guid": "f482029fdb59d5349b2ad8259a4015df",
      "type": 2
    },
    {
      "fileID": 1972364587465883,
      "guid": "7a584bd56363dcd47b1cf4607acf7616",
      "type": 2
    },
    {
      "fileID": 1829198217806200,
      "guid": "396e84a72c85e634caa93b680213eb5b",
      "type": 2
    }
  ],
  "Tier5Skills__2": [
    {
      "fileID": 1639015182491661,
      "guid": "71e0b9c539f03ac46bdfda97d6baff81",
      "type": 2
    },
    {
      "fileID": 1832746634248003,
      "guid": "f746d869a51636f4a8909ed281cc8a10",
      "type": 2
    },
    {
      "fileID": 1922232379908973,
      "guid": "a5501585c677d7c48adae711930008a3",
      "type": 2
    }
  ],
  "Tier1Skills__3": [
    {
      "fileID": 1210478171372487,
      "guid": "2aa959f40cf51f54c9a2f733c3cc3078",
      "type": 2
    }
  ],
  "Tier2Skills__3": [
    {
      "fileID": 1646899529702950,
      "guid": "660a8b60654b86340a3fab59fe32fcac",
      "type": 2
    },
    {
      "fileID": 1921874275492894,
      "guid": "8ac1b57211b4ee94d82b39413c71d74e",
      "type": 2
    },
    {
      "fileID": 1686759312923349,
      "guid": "70ed061ecba09af4283e724d2ce335b9",
      "type": 2
    }
  ],
  "Tier3Skills__3": [
    {
      "fileID": 1048467534227984,
      "guid": "5966aa158932bae438581183fbd37bf4",
      "type": 2
    },
    {
      "fileID": 1035518392929682,
      "guid": "e35ac9cf25c54e44c9fd65d853c2a2c1",
      "type": 2
    },
    {
      "fileID": 1296165490498852,
      "guid": "1639172c2d846294bbe0885a54593ae7",
      "type": 2
    }
  ],
  "Tier4Skills__3": [
    {
      "fileID": 1446023957395197,
      "guid": "81f789157660c414ea8d334a0f7bdcbf",
      "type": 2
    },
    {
      "fileID": 1349092676614706,
      "guid": "82c764a2e65205140a22ab26c5bccd93",
      "type": 2
    },
    {
      "fileID": 1046187329209521,
      "guid": "be50d663a2c42184a9127c2922bdebf1",
      "type": 2
    }
  ],
  "Tier5Skills__3": [
    {
      "fileID": 1187338392170639,
      "guid": "a2a38c26faa0f62499b784109a847a8d",
      "type": 2
    },
    {
      "fileID": 1586131067346528,
      "guid": "92bf680f271809742a3d962744849058",
      "type": 2
    },
    {
      "fileID": 1035518392929682,
      "guid": "e35ac9cf25c54e44c9fd65d853c2a2c1",
      "type": 2
    }
  ],
  "Tier1Skills__4": [
    {
      "fileID": 1865643612491285,
      "guid": "facbefa7ca14bfa459a0fd7511a9d8a6",
      "type": 2
    }
  ],
  "Tier2Skills__4": [
    {
      "fileID": 1512513469926870,
      "guid": "26d0e59ca149be749921b412839d36b1",
      "type": 2
    },
    {
      "fileID": 1121765038974368,
      "guid": "36f1935fe105a2247878761ec56281b8",
      "type": 2
    },
    {
      "fileID": 1955550795575206,
      "guid": "6cf7e2dc91e400444912d62d1683a836",
      "type": 2
    }
  ],
  "Tier3Skills__4": [
    {
      "fileID": 1554085315580172,
      "guid": "2d17e9f3f1ccd034794147a562cdd5a4",
      "type": 2
    },
    {
      "fileID": 1989158837562463,
      "guid": "ef5a2e563026cfb44985795cdd346a94",
      "type": 2
    },
    {
      "fileID": 1918707403924769,
      "guid": "55bec2edb3f3c1a4ea4058ba8b84ed7e",
      "type": 2
    }
  ],
  "Tier4Skills__4": [
    {
      "fileID": 1225199059914375,
      "guid": "fbb84ba00ce14c34da1caebbe019598d",
      "type": 2
    },
    {
      "fileID": 1075998793949093,
      "guid": "15cd27d603bf5f74c9b187dbb4fc159a",
      "type": 2
    },
    {
      "fileID": 1918707403924769,
      "guid": "55bec2edb3f3c1a4ea4058ba8b84ed7e",
      "type": 2
    }
  ],
  "Tier5Skills__4": [
    {
      "fileID": 1296165490498852,
      "guid": "1639172c2d846294bbe0885a54593ae7",
      "type": 2
    },
    {
      "fileID": 1867734379618117,
      "guid": "7244c5a3fc76a05449e6d5b270f3c10b",
      "type": 2
    },
    {
      "fileID": 1672316169124921,
      "guid": "c0e142dec885a054cae982f71e368a00",
      "type": 2
    }
  ],
  "Bio": "These courageous feline creatures roam the mountains for wild beasts to slay. They originated from an ordinary kitten that set out to find its lost master.",
  "History": "They say that there once was a legendary knight by the name of Siegfried. He had put his blade down on a field of grass, when an ordinary kitten with gray fur came and sat upon the blade. Siegfried took the kitten as his pet and brought it to his keep, where the cat lounged many evenings before the hearth. Eventually, Siegfried rode out on an adventure from which he never returned. The cat missed its master and went to look for him. Eventually, it found Siegfried's blade, but there was no trace of the cat's valiant master. The cat sat upon the blade just as it had done so many years ago and waited eagerly for its master's return. After many days and nights had passed, the cat decided that it would bring the blade to its master. Cats are stubborn creatures, and so the cat learned to carry the sword with its paws. As it dragged the sword through the countryside, the cat's physique changed gradually until it became the first Catzerker. However, it never found its master in all of its nine lives.",
  "StatOrientation": 1
}